fredeco/__init__.py
fredeco/fredData.py
fredeco/fredKey.py
fredeco/fredSearch.py
fredeco-0.1.1.dist-info/METADATA
fredeco-0.1.1.dist-info/WHEEL
fredeco-0.1.1.dist-info/RECORD
