Metadata-Version: 2.1
Name: fredeco
Version: 0.1.1
Summary: This python package allows its users to retrieve data provided by FRED® API and information related to them, such as their source.
Home-page: https://github.com/raulincadet/fredeco
License: MIT
Keywords: economics,data,indicators,fred
Author: Raulin L. Cadet
Maintainer: Raulin L. Cadet
Requires-Python: >=3.11,<4.0
Classifier: Development Status :: 4 - Beta
Classifier: Intended Audience :: Financial and Insurance Industry
Classifier: Intended Audience :: Science/Research
Classifier: License :: OSI Approved :: MIT License
Classifier: Programming Language :: Python :: 3
Classifier: Programming Language :: Python :: 3.11
Requires-Dist: datetime (>=5.1,<6.0)
Requires-Dist: nbsphinx (>=0.9.2,<0.10.0)
Requires-Dist: numpy (>=1.25.0,<2.0.0)
Requires-Dist: pandas (>=2.0.3,<3.0.0)
Requires-Dist: pandoc (>=2.3,<3.0)
Requires-Dist: requests (>=2.31.0,<3.0.0)
Project-URL: Documentation, https://fredeco.readthedocs.io/en/latest/
Project-URL: Repository, https://github.com/raulincadet/fredeco
